{
    "file_memory_usage": 1376.277660369873,
    "disk_memory_usage": 2655.7457885742188,
    "column_stats": [
        {
            "column": "YEAR",
            "memory_usage": 44.396175384521484,
            "fraction_of_total": 0.016717027501474947,
            "dtype": "int64"
        },
        {
            "column": "MONTH",
            "memory_usage": 44.396175384521484,
            "fraction_of_total": 0.016717027501474947,
            "dtype": "int64"
        },
        {
            "column": "DAY",
            "memory_usage": 44.396175384521484,
            "fraction_of_total": 0.016717027501474947,
            "dtype": "int64"
        },
        {
            "column": "DAY_OF_WEEK",
            "memory_usage": 44.396175384521484,
            "fraction_of_total": 0.016717027501474947,
            "dtype": "int64"
        },
        {
            "column": "FLIGHT_NUMBER",
            "memory_usage": 44.396175384521484,
            "fraction_of_total": 0.016717027501474947,
            "dtype": "int64"
        },
        {
            "column": "SCHEDULED_DEPARTURE",
            "memory_usage": 44.396175384521484,
            "fraction_of_total": 0.016717027501474947,
            "dtype": "int64"
        },
        {
            "column": "DEPARTURE_TIME",
            "memory_usage": 44.396175384521484,
            "fraction_of_total": 0.016717027501474947,
            "dtype": "float64"
        },
        {
            "column": "DEPARTURE_DELAY",
            "memory_usage": 44.396175384521484,
            "fraction_of_total": 0.016717027501474947,
            "dtype": "float64"
        },
        {
            "column": "TAXI_OUT",
            "memory_usage": 44.396175384521484,
            "fraction_of_total": 0.016717027501474947,
            "dtype": "float64"
        },
        {
            "column": "WHEELS_OFF",
            "memory_usage": 44.396175384521484,
            "fraction_of_total": 0.016717027501474947,
            "dtype": "float64"
        },
        {
            "column": "SCHEDULED_TIME",
            "memory_usage": 44.396175384521484,
            "fraction_of_total": 0.016717027501474947,
            "dtype": "float64"
        },
        {
            "column": "ELAPSED_TIME",
            "memory_usage": 44.396175384521484,
            "fraction_of_total": 0.016717027501474947,
            "dtype": "float64"
        },
        {
            "column": "AIR_TIME",
            "memory_usage": 44.396175384521484,
            "fraction_of_total": 0.016717027501474947,
            "dtype": "float64"
        },
        {
            "column": "DISTANCE",
            "memory_usage": 44.396175384521484,
            "fraction_of_total": 0.016717027501474947,
            "dtype": "int64"
        },
        {
            "column": "WHEELS_ON",
            "memory_usage": 44.396175384521484,
            "fraction_of_total": 0.016717027501474947,
            "dtype": "float64"
        },
        {
            "column": "TAXI_IN",
            "memory_usage": 44.396175384521484,
            "fraction_of_total": 0.016717027501474947,
            "dtype": "float64"
        },
        {
            "column": "SCHEDULED_ARRIVAL",
            "memory_usage": 44.396175384521484,
            "fraction_of_total": 0.016717027501474947,
            "dtype": "int64"
        },
        {
            "column": "ARRIVAL_TIME",
            "memory_usage": 44.396175384521484,
            "fraction_of_total": 0.016717027501474947,
            "dtype": "float64"
        },
        {
            "column": "ARRIVAL_DELAY",
            "memory_usage": 44.396175384521484,
            "fraction_of_total": 0.016717027501474947,
            "dtype": "float64"
        },
        {
            "column": "DIVERTED",
            "memory_usage": 44.396175384521484,
            "fraction_of_total": 0.016717027501474947,
            "dtype": "int64"
        },
        {
            "column": "CANCELLED",
            "memory_usage": 44.396175384521484,
            "fraction_of_total": 0.016717027501474947,
            "dtype": "int64"
        },
        {
            "column": "AIR_SYSTEM_DELAY",
            "memory_usage": 44.396175384521484,
            "fraction_of_total": 0.016717027501474947,
            "dtype": "float64"
        },
        {
            "column": "SECURITY_DELAY",
            "memory_usage": 44.396175384521484,
            "fraction_of_total": 0.016717027501474947,
            "dtype": "float64"
        },
        {
            "column": "AIRLINE_DELAY",
            "memory_usage": 44.396175384521484,
            "fraction_of_total": 0.016717027501474947,
            "dtype": "float64"
        },
        {
            "column": "LATE_AIRCRAFT_DELAY",
            "memory_usage": 44.396175384521484,
            "fraction_of_total": 0.016717027501474947,
            "dtype": "float64"
        },
        {
            "column": "WEATHER_DELAY",
            "memory_usage": 44.396175384521484,
            "fraction_of_total": 0.016717027501474947,
            "dtype": "float64"
        },
        {
            "column": "CANCELLATION_REASON",
            "memory_usage": 179.81304550170898,
            "fraction_of_total": 0.0677071752406862,
            "dtype": "object"
        },
        {
            "column": "ORIGIN_AIRPORT",
            "memory_usage": 322.52278327941895,
            "fraction_of_total": 0.12144339441937727,
            "dtype": "object"
        },
        {
            "column": "DESTINATION_AIRPORT",
            "memory_usage": 322.52278327941895,
            "fraction_of_total": 0.12144339441937727,
            "dtype": "object"
        },
        {
            "column": "AIRLINE",
            "memory_usage": 327.4209909439087,
            "fraction_of_total": 0.12328777564199399,
            "dtype": "object"
        },
        {
            "column": "TAIL_NUMBER",
            "memory_usage": 349.16940212249756,
            "fraction_of_total": 0.13147696727025782,
            "dtype": "object"
        }
    ]
}